{
  "namespace": "e",
  "name": "editor",
  "scripts": [
    "./file/File.script",
    "./parser/Parser.script",
    "./events/ModuleEvent.script",
    "./plugins/PluginManager.script",
    "./events/EventManager.script"
  ],
  "components": [
    "./plugins/PluginBase.xml"
  ],
  "classes": {
    "EditorMain": "./EditorMain.xml",
    "ProjectView": "./projectViews/ProjectView.xml",
    "ModuleView": "./moduleView/ModuleView.xml",
    "AttributeEditor": "./panels/AttributeEditor.xml"
  },
  "data": [
    "./data/ProjectData.json"
  ]
}